{
  "fetchedAt": "2026-07-14T10:55:39.236Z",
  "marketAsOf": "2026-07-14T10:55:39.228Z",
  "date": "2026-07-14",
  "validation": "passed",
  "report": "1. 🌐【全球宏觀與資金流向】：\n昨夜美股四大指數表現分化，標普500上漲，費半指數則顯示科技股動能持續。道瓊指數反映傳產股穩健，然那斯達克指數微幅震盪。美元指數缺失數據，然近期美元走弱趨勢可能持續，預期新台幣匯率將有升值壓力，外資在台股現貨市場可能維持買超。\n\n2. 📈【今日台股量價結構與權值展望】：\n預估今日台股開盤氣氛偏多，量能有望放大。台積電ADR昨夜收高，將對台股半導體權值股形成正面推動，聯發科與鴻海等權值股或受激勵。需關注日月光ADR數據缺失對市場情緒的潛在影響。\n\n3. 🛡️【金融與傳產防禦板塊評估】：\n在大盤高位震盪下，金融股特別是壽險金控如富邦金，具備資金避風港特質。公股行庫因放款穩定性，亦具備防禦性。傳產板塊中，傳統產業如鋼鐵與塑化可望成為資金流入重點。\n\n4. 🎯【焦點核心個股短線策略】：\n- 台燿 (6274): 現價1570元，短線支撐位於1500元，觀察價1600元，建議於支撐位加碼。\n- 昇陽半導體 (8028): 現價312.5元，支撐位300元，觀察價320元，建議於觀察價附近逢高減碼。\n- 富邦金 (2881): 現價124.5元，支撐位120元，觀察價126元，建議於支撐位以下布局。"
}
